hello_cli/__init__.py
hello_cli/cli.py
hello_cli_jdf-0.1.0.dist-info/licenses/LICENSE
hello_cli_jdf-0.1.0.dist-info/METADATA
hello_cli_jdf-0.1.0.dist-info/WHEEL
hello_cli_jdf-0.1.0.dist-info/entry_points.txt
hello_cli_jdf-0.1.0.dist-info/top_level.txt
hello_cli_jdf-0.1.0.dist-info/RECORD
