Metadata-Version: 2.4
Name: hello-cli-jdf
Version: 0.1.0
Summary: A simple CLI tool that says hi
Author-email: James Furtado <jamesdfurtado@gmail.com>
Requires-Python: >=3.7
License-File: LICENSE
Dynamic: license-file
